geogrid_dask/__init__.py
geogrid_dask/__main__.py
geogrid_dask/py.typed
geogrid_dask/server/main.py
geogrid_dask-0.0.3.dist-info/LICENSE
geogrid_dask-0.0.3.dist-info/METADATA
geogrid_dask-0.0.3.dist-info/WHEEL
geogrid_dask-0.0.3.dist-info/entry_points.txt
geogrid_dask-0.0.3.dist-info/RECORD
