Metadata-Version: 2.1
Name: geogrid-dask
Version: 0.0.3
Summary: Geogrid Dask
Home-page: https://github.com/Giangblackk/geogrid-dask
License: GPL-3.0
Author: Giang Ngo
Author-email: giangblackk@gmail.com
Requires-Python: >=3.9,<4.0
Classifier: Development Status :: 1 - Planning
Classifier: License :: OSI Approved :: GNU General Public License v3 (GPLv3)
Classifier: Programming Language :: Python :: 3
Classifier: Programming Language :: Python :: 3.9
Classifier: Programming Language :: Python :: 3.10
Classifier: Programming Language :: Python :: 3.11
Requires-Dist: bokeh (>=3.2.2,<4.0.0)
Requires-Dist: click (>=8.0.1)
Requires-Dist: dask[distributed] (>=2023.8.0,<2024.0.0)
Requires-Dist: fastapi (>=0.101.1,<0.102.0)
Requires-Dist: uvicorn[standard] (>=0.23.2,<0.24.0)
Project-URL: Changelog, https://github.com/Giangblackk/geogrid-dask/releases
Project-URL: Documentation, https://geogrid-dask.readthedocs.io
Project-URL: Repository, https://github.com/Giangblackk/geogrid-dask
